KSPython/BoosterParts.py
KSPython/KSPython.py
KSPython/LiquidEngineParts.py
KSPython/RocketFuelTankParts.py
KSPython/__init__.py
KSPython-0.1.1.dist-info/LICENSE
KSPython-0.1.1.dist-info/METADATA
KSPython-0.1.1.dist-info/WHEEL
KSPython-0.1.1.dist-info/top_level.txt
KSPython-0.1.1.dist-info/RECORD
