Metadata-Version: 2.1
Name: KSPython
Version: 0.1.1
Summary: A package made for plan and develop rockets in KSP
Home-page: UNKNOWN
Author: Luiz Frederico Villalobos
Author-email: luizf.villalobos@gmail.com
License: UNKNOWN
Platform: UNKNOWN
Classifier: Programming Language :: Python :: 3
Classifier: License :: OSI Approved :: MIT License
Classifier: Operating System :: OS Independent
Requires-Python: >=3.7
